setup.py
filecoin/__init__.py
filecoin/utils.py
filecoin.egg-info/PKG-INFO
filecoin.egg-info/SOURCES.txt
filecoin.egg-info/dependency_links.txt
filecoin.egg-info/requires.txt
filecoin.egg-info/top_level.txt
filecoin/api/__init__.py
filecoin/api/block.py
filecoin/api/docker.py
filecoin/api/miner.py
filecoin/api/node.py
filecoin/api/wallet.py