Metadata-Version: 1.0
Name: filecoin
Version: 0.0.1
Summary: filecoin
Home-page: UNKNOWN
Author: UNKNOWN
Author-email: UNKNOWN
License: UNKNOWN
Platform: linux
